icc_pro/__init__.py
icc_pro/accumulations.py
icc_pro/analog_inputs.py
icc_pro/core.py
icc_pro/field_units.py
icc_pro/meters.py
icc_pro/programs.py
icc_pro/sensors.py
icc_pro/token.py
icc_pro/valves.py
icc_pro/virtual_meters.py
ezapi_icc_pro-0.3.1.dist-info/LICENSE
ezapi_icc_pro-0.3.1.dist-info/METADATA
ezapi_icc_pro-0.3.1.dist-info/WHEEL
ezapi_icc_pro-0.3.1.dist-info/top_level.txt
ezapi_icc_pro-0.3.1.dist-info/RECORD
