Metadata-Version: 2.1
Name: ezapi-icc-pro
Version: 0.3.1
Summary: A Python wrapper for ICC PRO RESTful API
Author-email: Zeheng Li <imzehengl@gmail.com>
Maintainer-email: Zeheng Li <imzehengl@gmail.com>
Project-URL: repository, https://github.com/zehengl/ezapi-icc-pro
Project-URL: homepage, https://zehengl.github.io/ezapi-icc-pro/
Keywords: ICC PRO
Classifier: Programming Language :: Python :: 3
Classifier: License :: OSI Approved :: MIT License
Classifier: Operating System :: OS Independent
Requires-Python: >=3.8
License-File: LICENSE
Requires-Dist: requests
Requires-Dist: wrapt ==1.16.0
